LICENSE.txt
MANIFEST.in
README.rst
setup.cfg
setup.py
simple_salesforce/__init__.py
simple_salesforce/__version__.py
simple_salesforce/api.py
simple_salesforce/bulk.py
simple_salesforce/exceptions.py
simple_salesforce/format.py
simple_salesforce/login.py
simple_salesforce/messages.py
simple_salesforce/metadata.py
simple_salesforce/util.py
simple_salesforce_propic.egg-info/PKG-INFO
simple_salesforce_propic.egg-info/SOURCES.txt
simple_salesforce_propic.egg-info/dependency_links.txt
simple_salesforce_propic.egg-info/requires.txt
simple_salesforce_propic.egg-info/top_level.txt