Metadata-Version: 1.2
Name: simple-salesforce-propic
Version: 0.74.5
Summary: A basic Salesforce.com REST API client.
Home-page: https://github.com/simple-salesforce/simple-salesforce
Author: Nick Catalano
Author-email: nickcatal@gmail.com
Maintainer: Demian Brecht
Maintainer-email: demianbrecht@gmail.com
License: Apache 2.0
Keywords: python salesforce salesforce.com
Platform: UNKNOWN
Classifier: Development Status :: 5 - Production/Stable
Classifier: License :: OSI Approved :: Apache Software License
Classifier: Intended Audience :: Developers
Classifier: Intended Audience :: System Administrators
Classifier: Operating System :: OS Independent
Classifier: Topic :: Internet :: WWW/HTTP
Classifier: Programming Language :: Python :: 3.5
Classifier: Programming Language :: Python :: 3.6
Classifier: Programming Language :: Python :: 3.7
Classifier: Programming Language :: Python :: 3.8
Classifier: Programming Language :: Python :: Implementation :: PyPy
